bitbucket/__init__.py
bitbucket/aclient.py
bitbucket/base.py
bitbucket/client.py
bitbucket/exceptions.py
bitbucket_python-0.3.1.dist-info/LICENSE
bitbucket_python-0.3.1.dist-info/METADATA
bitbucket_python-0.3.1.dist-info/WHEEL
bitbucket_python-0.3.1.dist-info/RECORD
